llama_index/storage/kvstore/mongodb/__init__.py
llama_index/storage/kvstore/mongodb/base.py
flying_delta_storage_kvstore_mongodb-0.1.0.dist-info/METADATA
flying_delta_storage_kvstore_mongodb-0.1.0.dist-info/WHEEL
flying_delta_storage_kvstore_mongodb-0.1.0.dist-info/RECORD
